Topsis/__init__.py
Topsis/topsis.py
Topsis_BhagwanBansal_101903015-1.0.0.dist-info/LICENSE
Topsis_BhagwanBansal_101903015-1.0.0.dist-info/METADATA
Topsis_BhagwanBansal_101903015-1.0.0.dist-info/WHEEL
Topsis_BhagwanBansal_101903015-1.0.0.dist-info/top_level.txt
Topsis_BhagwanBansal_101903015-1.0.0.dist-info/RECORD
