Metadata-Version: 2.1
Name: Topsis-BhagwanBansal-101903015
Version: 1.0.0
Summary: A Topsis package developed by BHAGWAN BANSAL
Author: Bhagwan Bansal
Author-email: <bbansal_be19@thapar.edu>
License: UNKNOWN
Platform: UNKNOWN
Classifier: Development Status :: 1 - Planning
Classifier: Intended Audience :: Developers
Classifier: Programming Language :: Python :: 3
Classifier: Operating System :: Unix
Classifier: Operating System :: MacOS :: MacOS X
Classifier: Operating System :: Microsoft :: Windows
License-File: LICENSE
